wedomldump/__init__.py
wedomldump/command.py
wedomldump/main.py
wedomldump/mldump.py
wedomldump-0.0.1.dist-info/METADATA
wedomldump-0.0.1.dist-info/WHEEL
wedomldump-0.0.1.dist-info/entry_points.txt
wedomldump-0.0.1.dist-info/top_level.txt
wedomldump-0.0.1.dist-info/RECORD
